{
  "country": "Ukraine",
  "regions": {
    "Cherkasy": "ck",
    "Chernihiv": "ch",
    "Chernivtsi": "cv",
    "Crimea": "kr",
    "Dnipropetrovs'k": "dp",
    "Donets'k": "dt",
    "Ivano-Frankivs'k": "if",
    "Kharkiv": "kk",
    "Kherson": "ks",
    "Khmel'nyts'kyy": "km",
    "Kiev": "kv",
    "Kiev City": "kc",
    "Kirovohrad": "kh",
    "L'viv": "lv",
    "Luhans'k": "lh",
    "Mykolayiv": "my",
    "Odessa": "od",
    "Poltava": "pl",
    "Rivne": "rv",
    "Sevastopol'": "sc",
    "Sumy": "sm",
    "Ternopil'": "tp",
    "Transcarpathia": "zk",
    "Vinnytsya": "vi",
    "Volyn": "vo",
    "Zaporizhzhya": "zp",
    "Zhytomyr": "zt"
  },
  "index": {
    "Cherkasy, admin2": "countries/ua/ua-ck-all.js",
    "Chernihiv, admin2": "countries/ua/ua-ch-all.js",
    "Chernivtsi, admin2": "countries/ua/ua-cv-all.js",
    "Crimea, admin2": "countries/ua/ua-kr-all.js",
    "Dnipropetrovs'k, admin2": "countries/ua/ua-dp-all.js",
    "Donets'k, admin2": "countries/ua/ua-dt-all.js",
    "Ivano-Frankivs'k, admin2": "countries/ua/ua-if-all.js",
    "Kharkiv, admin2": "countries/ua/ua-kk-all.js",
    "Kherson, admin2": "countries/ua/ua-ks-all.js",
    "Khmel'nyts'kyy, admin2": "countries/ua/ua-km-all.js",
    "Kiev, admin2": "countries/ua/ua-kv-all.js",
    "Kiev City, admin2": "countries/ua/ua-kc-all.js",
    "Kirovohrad, admin2": "countries/ua/ua-kh-all.js",
    "L'viv, admin2": "countries/ua/ua-lv-all.js",
    "Luhans'k, admin2": "countries/ua/ua-lh-all.js",
    "Mykolayiv, admin2": "countries/ua/ua-my-all.js",
    "Odessa, admin2": "countries/ua/ua-od-all.js",
    "Poltava, admin2": "countries/ua/ua-pl-all.js",
    "Rivne, admin2": "countries/ua/ua-rv-all.js",
    "Sevastopol', admin2": "countries/ua/ua-sc-all.js",
    "Sumy, admin2": "countries/ua/ua-sm-all.js",
    "Ternopil', admin2": "countries/ua/ua-tp-all.js",
    "Transcarpathia, admin2": "countries/ua/ua-zk-all.js",
    "Vinnytsya, admin2": "countries/ua/ua-vi-all.js",
    "Volyn, admin2": "countries/ua/ua-vo-all.js",
    "Zaporizhzhya, admin2": "countries/ua/ua-zp-all.js",
    "Zhytomyr, admin2": "countries/ua/ua-zt-all.js"
  },
  "script": "<script src='maps/ua/ua-admin2-all.js'></script>"
}